fprime_fpy-0.3.1.dist-info/licenses/LICENSE
fpy/SPEC.md
fpy/__init__.py
fpy/codegen.py
fpy/compiler.py
fpy/desugaring.py
fpy/error.py
fpy/grammar.lark
fpy/ir.py
fpy/macros.py
fpy/main.py
fpy/model.py
fpy/semantics.py
fpy/syntax.py
fpy/test_helpers.py
fpy/types.py
fpy/bytecode/SPEC.md
fpy/bytecode/__init__.py
fpy/bytecode/assembler.py
fpy/bytecode/directives.py
fpy/bytecode/grammar.lark
fprime_fpy-0.3.1.dist-info/METADATA
fprime_fpy-0.3.1.dist-info/WHEEL
fprime_fpy-0.3.1.dist-info/entry_points.txt
fprime_fpy-0.3.1.dist-info/top_level.txt
fprime_fpy-0.3.1.dist-info/RECORD
