Metadata-Version: 2.4
Name: fprime-fpy
Version: 0.3.1
Summary: Fpy Advanced Sequencing Language for F Prime
Author-email: Zimri Leisher <zimri.leisher@gmail.com>, Michael Starch <Michael.D.Starch@jpl.nasa.gov>
Project-URL: Homepage, https://fprime.jpl.nasa.gov
Project-URL: Documentation, https://nasa.github.io/fprime/
Project-URL: Repository, https://github.com/fprime-community/fpy
Keywords: fprime,embedded,nasa,flight,software
Classifier: Development Status :: 4 - Beta
Classifier: Intended Audience :: Developers
Classifier: Operating System :: Unix
Classifier: Operating System :: POSIX
Classifier: Programming Language :: Python
Classifier: Programming Language :: Python :: 3
Classifier: Programming Language :: Python :: 3.9
Classifier: Programming Language :: Python :: 3.10
Classifier: Programming Language :: Python :: 3.11
Classifier: Programming Language :: Python :: 3.12
Classifier: Programming Language :: Python :: 3.13
Classifier: Programming Language :: Python :: Implementation :: CPython
Classifier: Programming Language :: Python :: Implementation :: PyPy
Classifier: License :: OSI Approved :: Apache Software License
Requires-Python: >=3.9
License-File: LICENSE
Requires-Dist: pytest>=6.2.4
Requires-Dist: fprime-gds>=3.4.3
Requires-Dist: lark>=1.2.2
Dynamic: license-file
